rsi/__init__.py
rsi/__main__.py
rsi/direction.py
rsi/rsi.py
rsi/state.py
RSI.py-1.2.1.dist-info/LICENSE
RSI.py-1.2.1.dist-info/METADATA
RSI.py-1.2.1.dist-info/WHEEL
RSI.py-1.2.1.dist-info/entry_points.txt
RSI.py-1.2.1.dist-info/top_level.txt
RSI.py-1.2.1.dist-info/RECORD
